UMNN/MonotonicNN.py
UMNN/NeuralIntegral.py
UMNN/ParallelNeuralIntegral.py
UMNN/UMNNMAF.py
UMNN/UMNNMAFFlow.py
UMNN/__init__.py
UMNN/made.py
UMNN/spectral_normalization.py
umnn-1.71.dist-info/METADATA
umnn-1.71.dist-info/WHEEL
umnn-1.71.dist-info/licenses/LICENSE
umnn-1.71.dist-info/RECORD
